functional_flow/__init__.py
functional_flow-0.0.1.dist-info/METADATA
functional_flow-0.0.1.dist-info/WHEEL
functional_flow-0.0.1.dist-info/licenses/LICENSE
functional_flow-0.0.1.dist-info/RECORD
