Metadata-Version: 2.1
Name: functional_flow
Version: 0.0.1
Summary: A small library for the compose and flow functions.
Project-URL: Homepage, https://github.com/sko-2/functional-flow
Project-URL: Bug Tracker, https://github.com/sko-2/functional-flow/issues
Author-email: sko2 <sko2.dev@gmail.com>
License-File: LICENSE
Classifier: License :: OSI Approved :: MIT License
Classifier: Operating System :: OS Independent
Classifier: Programming Language :: Python :: 3
Requires-Python: >=3.7
